julia_project_basic/__init__.py
julia_project_basic/basic.py
julia_project_basic-0.1.7.dist-info/LICENSE.md
julia_project_basic-0.1.7.dist-info/METADATA
julia_project_basic-0.1.7.dist-info/WHEEL
julia_project_basic-0.1.7.dist-info/top_level.txt
julia_project_basic-0.1.7.dist-info/RECORD
