Metadata-Version: 2.1
Name: julia-project-basic
Version: 0.1.7
Summary: Ensure that Julia packages are installed correctly
License: MIT
Project-URL: Home, http://github.com/jlapeyre/julia_project_basic
Classifier: Framework :: Django
Classifier: License :: OSI Approved :: MIT License
Classifier: Programming Language :: Python :: 3
License-File: LICENSE.md
Requires-Dist: find-libpython
Requires-Dist: tomli
